MANIFEST.in
README.rst
setup.cfg
setup.py
shisensho/__init__.py
shisensho/__main__.py
shisensho/about.py
shisensho/board.py
shisensho/boardEvent.py
shisensho/clock.py
shisensho/configShisen.py
shisensho/dialog.py
shisensho/log.py
shisensho/matchTiles.py
shisensho/matrixTile.py
shisensho/shisenException.py
shisensho/shisensho.py
shisensho/tileSource.py
shisensho/tileboard.py
shisensho/window.py
shisensho.egg-info/PKG-INFO
shisensho.egg-info/SOURCES.txt
shisensho.egg-info/dependency_links.txt
shisensho.egg-info/entry_points.txt
shisensho.egg-info/requires.txt
shisensho.egg-info/top_level.txt
shisensho/data/config.json
shisensho/data/tiles-unicode.gif
shisensho/data/tilescolor3.png
shisensho/wallpapers/atardecer.jpg
shisensho/wallpapers/bosque.jpg
shisensho/wallpapers/flores.jpg
shisensho/wallpapers/otoño.jpg
shisensho/wallpapers/peces.jpg
shisensho/wallpapers/playa.jpg
shisensho/wallpapers/puertomar.jpg
shisensho/wallpapers/wallpaper1.jpg