Metadata-Version: 1.1
Name: shisensho
Version: 0.9.12
Summary: Shisen Sho Game
Home-page: https://github.com/apolinux/shisensho
Author: Carlos Arce
Author-email: apolinux@gmail.com
License: Apache 2
Keywords: shisensho,game,board game,shisen
Platform: UNKNOWN
Classifier: Development Status :: 3 - Alpha
Classifier: Intended Audience :: End Users/Desktop
Classifier: Topic :: Games/Entertainment :: Board Games
Classifier: License :: OSI Approved :: Apache Software License
Classifier: Programming Language :: Python :: 3
Classifier: Programming Language :: Python :: 3.3
Classifier: Programming Language :: Python :: 3.4
Classifier: Programming Language :: Python :: 3.5
